{
  "id": null,
  "name": "ei007",
  "title": "ei007",
  "description": "Scraped from unknown source",
  "width": 200,
  "height": 200,
  "userId": "scraper",
  "projectId": null,
  "isPublic": false,
  "createdAt": "2025-08-05T12:46:21.394470Z",
  "updatedAt": "2025-08-05T12:46:21.394491Z",
  "syncStatus": "synced",
  "isTemporary": false,
  "data": {
    "backgroundColor": "#ffffff",
    "background": {
      "type": "solid",
      "color": "#ffffff"
    },
    "animationSettings": [
      {
        "delay": "0.5s",
        "duration": "0.4s",
        "elementId": "BG-img",
        "fillMode": "forwards",
        "iterationCount": "1",
        "name": "gwd-gen-1tergwdanimation_gwd-keyframes_start",
        "timingFunction": "linear"
      },
      {
        "delay": "0s",
        "duration": "0.4s",
        "elementId": "Shape-red",
        "fillMode": "forwards",
        "iterationCount": "1",
        "name": "gwd-gen-1qqxgwdanimation_gwd-keyframes_start",
        "timingFunction": "linear"
      },
      {
        "delay": "0.2s",
        "duration": "0.4s",
        "elementId": "Footer-outline",
        "fillMode": "forwards",
        "iterationCount": "1",
        "name": "gwd-gen-tepwgwdanimation_gwd-keyframes_start",
        "timingFunction": "linear"
      },
      {
        "delay": "0.2s",
        "duration": "0.4s",
        "elementId": "Footer",
        "fillMode": "forwards",
        "iterationCount": "1",
        "name": "gwd-gen-14a9gwdanimation_gwd-keyframes_start",
        "timingFunction": "linear"
      },
      {
        "delay": "0.9s",
        "duration": "0.5s",
        "elementId": "Heading1",
        "fillMode": "forwards",
        "iterationCount": "1",
        "name": "gwd-gen-1j11gwdanimation_gwd-keyframes_start",
        "timingFunction": "linear"
      },
      {
        "delay": "1.1s",
        "duration": "0.5s",
        "elementId": "Heading2",
        "fillMode": "forwards",
        "iterationCount": "1",
        "name": "gwd-gen-r48hgwdanimation_gwd-keyframes_start",
        "timingFunction": "linear"
      },
      {
        "delay": "1.5s",
        "duration": "0.5s",
        "elementId": "Tagline",
        "fillMode": "forwards",
        "iterationCount": "1",
        "name": "gwd-gen-1tvogwdanimation_gwd-keyframes_start",
        "timingFunction": "linear"
      },
      {
        "delay": "1.9s",
        "duration": "0.3s",
        "elementId": "Logo",
        "fillMode": "forwards",
        "iterationCount": "1",
        "name": "gwd-gen-15axgwdanimation_gwd-keyframes_start",
        "timingFunction": "linear"
      },
      {
        "delay": "2.2s",
        "duration": "0.5s",
        "elementId": "Text",
        "fillMode": "forwards",
        "iterationCount": "1",
        "name": "gwd-gen-1kzagwdanimation_gwd-keyframes_start",
        "timingFunction": "linear"
      },
      {
        "delay": "2.6s",
        "duration": "0.4s",
        "elementId": "Call-To-Action",
        "fillMode": "forwards",
        "iterationCount": "1",
        "name": "gwd-gen-6zaogwdanimation_gwd-keyframes_start",
        "timingFunction": "linear"
      }
    ],
    "customProperties": {
      "sourceUrl": null,
      "scrapedAt": "2025-08-05 01:06:51",
      "bannerType": "html5",
      "originalSize": "200x200"
    },
    "globalStyles": {
      "keyframes": {
        "gwd-empty-animation": {
          "name": "gwd-empty-animation",
          "rules": [
            {
              "keyText": "0%",
              "style": "opacity: 0.001;"
            },
            {
              "keyText": "100%",
              "style": "opacity: 0;"
            }
          ]
        },
        "gwd-empty-animation_start": {
          "name": "gwd-empty-animation_start",
          "rules": [
            {
              "keyText": "0%",
              "style": "opacity: 0.001;"
            },
            {
              "keyText": "100%",
              "style": "opacity: 0;"
            }
          ]
        },
        "gwd-gen-14a9gwdanimation_gwd-keyframes": {
          "name": "gwd-gen-14a9gwdanimation_gwd-keyframes",
          "rules": [
            {
              "keyText": "0%",
              "style": "transform: translate3d(0px, 0px, 0px); opacity: 0; animation-timing-function: linear;"
            },
            {
              "keyText": "100%",
              "style": "transform: translate3d(-79px, -66px, 0px); opacity: 1; animation-timing-function: linear;"
            }
          ]
        },
        "gwd-gen-14a9gwdanimation_gwd-keyframes_start": {
          "name": "gwd-gen-14a9gwdanimation_gwd-keyframes_start",
          "rules": [
            {
              "keyText": "0%",
              "style": "transform: translate3d(0px, 0px, 0px); opacity: 0; animation-timing-function: linear;"
            },
            {
              "keyText": "100%",
              "style": "transform: translate3d(-79px, -66px, 0px); opacity: 1; animation-timing-function: linear;"
            }
          ]
        },
        "gwd-gen-15axgwdanimation_gwd-keyframes": {
          "name": "gwd-gen-15axgwdanimation_gwd-keyframes",
          "rules": [
            {
              "keyText": "0%",
              "style": "opacity: 0; transform: translate3d(0px, -2px, 0px); animation-timing-function: linear;"
            },
            {
              "keyText": "100%",
              "style": "opacity: 1; transform: translate3d(0px, -2px, 0px); animation-timing-function: linear;"
            }
          ]
        },
        "gwd-gen-15axgwdanimation_gwd-keyframes_start": {
          "name": "gwd-gen-15axgwdanimation_gwd-keyframes_start",
          "rules": [
            {
              "keyText": "0%",
              "style": "opacity: 0; transform: translate3d(0px, -2px, 0px); animation-timing-function: linear;"
            },
            {
              "keyText": "100%",
              "style": "opacity: 1; transform: translate3d(0px, -2px, 0px); animation-timing-function: linear;"
            }
          ]
        },
        "gwd-gen-1j11gwdanimation_gwd-keyframes": {
          "name": "gwd-gen-1j11gwdanimation_gwd-keyframes",
          "rules": [
            {
              "keyText": "0%",
              "style": "left: -70px; top: 81px; opacity: 0; transform: translate3d(0px, 0px, 0px) scale3d(1, 1, 1); width: 110px; animation-timing-function: linear;"
            },
            {
              "keyText": "60%",
              "style": "left: 31px; top: 81px; opacity: 1; transform: translate3d(-5px, 0px, 0px) scale3d(1.1, 1, 1); width: 110px; animation-timing-function: linear;"
            },
            {
              "keyText": "100%",
              "style": "left: 21px; top: 81px; opacity: 1; transform: translate3d(-11px, 0px, 0px) scale3d(1, 1, 1); width: 110px; animation-timing-function: linear;"
            }
          ]
        },
        "gwd-gen-1j11gwdanimation_gwd-keyframes_start": {
          "name": "gwd-gen-1j11gwdanimation_gwd-keyframes_start",
          "rules": [
            {
              "keyText": "0%",
              "style": "left: -70px; top: 81px; opacity: 0; transform: translate3d(0px, 0px, 0px) scale3d(1, 1, 1); width: 110px; animation-timing-function: linear;"
            },
            {
              "keyText": "60%",
              "style": "left: 31px; top: 81px; opacity: 1; transform: translate3d(-5px, 0px, 0px) scale3d(1.1, 1, 1); width: 110px; animation-timing-function: linear;"
            },
            {
              "keyText": "100%",
              "style": "left: 21px; top: 81px; opacity: 1; transform: translate3d(-11px, 0px, 0px) scale3d(1, 1, 1); width: 110px; animation-timing-function: linear;"
            }
          ]
        },
        "gwd-gen-1kzagwdanimation_gwd-keyframes": {
          "name": "gwd-gen-1kzagwdanimation_gwd-keyframes",
          "rules": [
            {
              "keyText": "0%",
              "style": "left: -177px; opacity: 0; top: 150px; animation-timing-function: ease-out;"
            },
            {
              "keyText": "60%",
              "style": "left: 10px; opacity: 1; top: 150px; animation-timing-function: linear;"
            },
            {
              "keyText": "100%",
              "style": "left: 0px; opacity: 1; top: 150px; animation-timing-function: linear;"
            }
          ]
        },
        "gwd-gen-1kzagwdanimation_gwd-keyframes_start": {
          "name": "gwd-gen-1kzagwdanimation_gwd-keyframes_start",
          "rules": [
            {
              "keyText": "0%",
              "style": "left: -177px; opacity: 0; top: 150px; animation-timing-function: ease-out;"
            },
            {
              "keyText": "60%",
              "style": "left: 10px; opacity: 1; top: 150px; animation-timing-function: linear;"
            },
            {
              "keyText": "100%",
              "style": "left: 0px; opacity: 1; top: 150px; animation-timing-function: linear;"
            }
          ]
        },
        "gwd-gen-1qqxgwdanimation_gwd-keyframes": {
          "name": "gwd-gen-1qqxgwdanimation_gwd-keyframes",
          "rules": [
            {
              "keyText": "0%",
              "style": "transform: translate3d(0px, 0px, 0px); opacity: 0; width: 200px; animation-timing-function: linear;"
            },
            {
              "keyText": "100%",
              "style": "transform: translate3d(47px, -110px, 0px); opacity: 1; width: 200px; animation-timing-function: linear;"
            }
          ]
        },
        "gwd-gen-1qqxgwdanimation_gwd-keyframes_start": {
          "name": "gwd-gen-1qqxgwdanimation_gwd-keyframes_start",
          "rules": [
            {
              "keyText": "0%",
              "style": "transform: translate3d(0px, 0px, 0px); opacity: 0; width: 200px; animation-timing-function: linear;"
            },
            {
              "keyText": "100%",
              "style": "transform: translate3d(47px, -110px, 0px); opacity: 1; width: 200px; animation-timing-function: linear;"
            }
          ]
        },
        "gwd-gen-1tergwdanimation_gwd-keyframes": {
          "name": "gwd-gen-1tergwdanimation_gwd-keyframes",
          "rules": [
            {
              "keyText": "0%",
              "style": "opacity: 0; animation-timing-function: linear;"
            },
            {
              "keyText": "100%",
              "style": "opacity: 1; animation-timing-function: linear;"
            }
          ]
        },
        "gwd-gen-1tergwdanimation_gwd-keyframes_start": {
          "name": "gwd-gen-1tergwdanimation_gwd-keyframes_start",
          "rules": [
            {
              "keyText": "0%",
              "style": "opacity: 0; animation-timing-function: linear;"
            },
            {
              "keyText": "100%",
              "style": "opacity: 1; animation-timing-function: linear;"
            }
          ]
        },
        "gwd-gen-1tvogwdanimation_gwd-keyframes": {
          "name": "gwd-gen-1tvogwdanimation_gwd-keyframes",
          "rules": [
            {
              "keyText": "0%",
              "style": "transform: translate3d(-21px, -34px, 0px) scale3d(0.001, 1, 1); animation-timing-function: linear;"
            },
            {
              "keyText": "60%",
              "style": "transform: translate3d(-21px, -34px, 0px) scale3d(1.07, 1, 1); animation-timing-function: linear;"
            },
            {
              "keyText": "100%",
              "style": "transform: translate3d(-21px, -34px, 0px) scale3d(1, 1, 1); animation-timing-function: linear;"
            }
          ]
        },
        "gwd-gen-1tvogwdanimation_gwd-keyframes_start": {
          "name": "gwd-gen-1tvogwdanimation_gwd-keyframes_start",
          "rules": [
            {
              "keyText": "0%",
              "style": "transform: translate3d(-21px, -34px, 0px) scale3d(0.001, 1, 1); animation-timing-function: linear;"
            },
            {
              "keyText": "60%",
              "style": "transform: translate3d(-21px, -34px, 0px) scale3d(1.07, 1, 1); animation-timing-function: linear;"
            },
            {
              "keyText": "100%",
              "style": "transform: translate3d(-21px, -34px, 0px) scale3d(1, 1, 1); animation-timing-function: linear;"
            }
          ]
        },
        "gwd-gen-6zaogwdanimation_gwd-keyframes": {
          "name": "gwd-gen-6zaogwdanimation_gwd-keyframes",
          "rules": [
            {
              "keyText": "0%",
              "style": "transform: translate3d(47px, 0px, 0px) scale3d(0.001, 0.001, 1); top: 135px; width: 66px; height: 67px; left: 46px; animation-timing-function: linear;"
            },
            {
              "keyText": "100%",
              "style": "transform: translate3d(87px, 0px, 0px) scale3d(1, 1, 1); top: 117px; width: 66px; height: 67px; left: 43px; animation-timing-function: linear;"
            }
          ]
        },
        "gwd-gen-6zaogwdanimation_gwd-keyframes_start": {
          "name": "gwd-gen-6zaogwdanimation_gwd-keyframes_start",
          "rules": [
            {
              "keyText": "0%",
              "style": "transform: translate3d(47px, 0px, 0px) scale3d(0.001, 0.001, 1); top: 135px; width: 66px; height: 67px; left: 46px; animation-timing-function: linear;"
            },
            {
              "keyText": "100%",
              "style": "transform: translate3d(87px, 0px, 0px) scale3d(1, 1, 1); top: 117px; width: 66px; height: 67px; left: 43px; animation-timing-function: linear;"
            }
          ]
        },
        "gwd-gen-r48hgwdanimation_gwd-keyframes": {
          "name": "gwd-gen-r48hgwdanimation_gwd-keyframes",
          "rules": [
            {
              "keyText": "0%",
              "style": "left: -70px; top: 114px; opacity: 0; transform: translate3d(0px, -10px, 0px) scale3d(1, 1, 1); animation-timing-function: linear;"
            },
            {
              "keyText": "60%",
              "style": "left: 31px; top: 114px; opacity: 1; transform: translate3d(-5px, -10px, 0px) scale3d(1.1, 1, 1); animation-timing-function: linear;"
            },
            {
              "keyText": "100%",
              "style": "left: 21px; top: 114px; opacity: 1; transform: translate3d(-11px, -10px, 0px) scale3d(1, 1, 1); animation-timing-function: linear;"
            }
          ]
        },
        "gwd-gen-r48hgwdanimation_gwd-keyframes_start": {
          "name": "gwd-gen-r48hgwdanimation_gwd-keyframes_start",
          "rules": [
            {
              "keyText": "0%",
              "style": "left: -70px; top: 114px; opacity: 0; transform: translate3d(0px, -10px, 0px) scale3d(1, 1, 1); animation-timing-function: linear;"
            },
            {
              "keyText": "60%",
              "style": "left: 31px; top: 114px; opacity: 1; transform: translate3d(-5px, -10px, 0px) scale3d(1.1, 1, 1); animation-timing-function: linear;"
            },
            {
              "keyText": "100%",
              "style": "left: 21px; top: 114px; opacity: 1; transform: translate3d(-11px, -10px, 0px) scale3d(1, 1, 1); animation-timing-function: linear;"
            }
          ]
        },
        "gwd-gen-tepwgwdanimation_gwd-keyframes": {
          "name": "gwd-gen-tepwgwdanimation_gwd-keyframes",
          "rules": [
            {
              "keyText": "0%",
              "style": "transform: translate3d(0px, 0px, 0px); opacity: 0; animation-timing-function: linear;"
            },
            {
              "keyText": "100%",
              "style": "transform: translate3d(-79px, -66px, 0px); opacity: 1; animation-timing-function: linear;"
            }
          ]
        },
        "gwd-gen-tepwgwdanimation_gwd-keyframes_start": {
          "name": "gwd-gen-tepwgwdanimation_gwd-keyframes_start",
          "rules": [
            {
              "keyText": "0%",
              "style": "transform: translate3d(0px, 0px, 0px); opacity: 0; animation-timing-function: linear;"
            },
            {
              "keyText": "100%",
              "style": "transform: translate3d(-79px, -66px, 0px); opacity: 1; animation-timing-function: linear;"
            }
          ]
        }
      }
    },
    "gridSettings": {
      "gridSize": 20,
      "showGrid": false,
      "snapToGrid": false,
      "snapToObjects": false,
      "snapTolerance": 5
    },
    "viewportSettings": {
      "zoom": 1,
      "panX": 0,
      "panY": 0
    }
  },
  "layers": [
    {
      "id": "BG-img",
      "type": "image",
      "name": "content-image",
      "visible": true,
      "locked": false,
      "zIndex": 0,
      "syncStatus": "synced",
      "isTemporary": false,
      "transform": {
        "x": 0.0,
        "y": 0.0,
        "width": 200.0,
        "height": 136.0,
        "rotation": 0.0,
        "scaleX": 1.0,
        "scaleY": 1.0,
        "opacity": 1.0
      },
      "properties": {
        "src": "assets/e8b6a6b914cc.jpg",
        "alt": null,
        "objectFit": "contain",
        "filters": {},
        "border": {},
        "shadow": {},
        "animations": [
          {
            "delay": "0.5s",
            "duration": "0.4s",
            "fillMode": "forwards",
            "iterationCount": "1",
            "name": "gwd-gen-1tergwdanimation_gwd-keyframes_start",
            "timingFunction": "linear"
          }
        ]
      }
    },
    {
      "id": "layer-1",
      "type": "image",
      "name": "content-image",
      "visible": true,
      "locked": false,
      "zIndex": 0,
      "syncStatus": "synced",
      "isTemporary": false,
      "transform": {
        "x": 0.0,
        "y": 0.0,
        "width": 200.0,
        "height": 136.0,
        "rotation": 0.0,
        "scaleX": 1.0,
        "scaleY": 1.0,
        "opacity": 1.0
      },
      "properties": {
        "src": "assets/e8b6a6b914cc.jpg",
        "alt": null,
        "objectFit": "contain",
        "filters": {},
        "border": {},
        "shadow": {},
        "animations": []
      }
    },
    {
      "id": "Shape-red",
      "type": "image",
      "name": "content-image",
      "visible": true,
      "locked": false,
      "zIndex": 0,
      "syncStatus": "synced",
      "isTemporary": false,
      "transform": {
        "x": 0.0,
        "y": 18.0,
        "width": 200.0,
        "height": 182.0,
        "rotation": 0.0,
        "scaleX": 1.0,
        "scaleY": 1.0,
        "opacity": 1.0
      },
      "properties": {
        "src": "assets/3c0d76b7f562.png",
        "alt": null,
        "objectFit": "contain",
        "filters": {},
        "border": {},
        "shadow": {},
        "animations": [
          {
            "delay": "0s",
            "duration": "0.4s",
            "fillMode": "forwards",
            "iterationCount": "1",
            "name": "gwd-gen-1qqxgwdanimation_gwd-keyframes_start",
            "timingFunction": "linear"
          }
        ]
      }
    },
    {
      "id": "layer-3",
      "type": "image",
      "name": "content-image",
      "visible": true,
      "locked": false,
      "zIndex": 0,
      "syncStatus": "synced",
      "isTemporary": false,
      "transform": {
        "x": 0.0,
        "y": 18.0,
        "width": 200.0,
        "height": 182.0,
        "rotation": 0.0,
        "scaleX": 1.0,
        "scaleY": 1.0,
        "opacity": 1.0
      },
      "properties": {
        "src": "assets/3c0d76b7f562.png",
        "alt": null,
        "objectFit": "contain",
        "filters": {},
        "border": {},
        "shadow": {},
        "animations": []
      }
    },
    {
      "id": "layer-12",
      "type": "image",
      "name": "content-image",
      "visible": true,
      "locked": false,
      "zIndex": 0,
      "syncStatus": "synced",
      "isTemporary": false,
      "transform": {
        "x": 40.0,
        "y": 42.0,
        "width": 50.0,
        "height": 33.0,
        "rotation": 0.0,
        "scaleX": 1.0,
        "scaleY": 1.0,
        "opacity": 1.0
      },
      "properties": {
        "src": "assets/8a1e00ae0172.png",
        "alt": null,
        "objectFit": "contain",
        "filters": {},
        "border": {},
        "shadow": {},
        "animations": []
      }
    },
    {
      "id": "Footer-outline",
      "type": "image",
      "name": "content-image",
      "visible": true,
      "locked": false,
      "zIndex": 0,
      "syncStatus": "synced",
      "isTemporary": false,
      "transform": {
        "x": 93.0,
        "y": 101.0,
        "width": 107.0,
        "height": 99.0,
        "rotation": 0.0,
        "scaleX": 1.0,
        "scaleY": 1.0,
        "opacity": 1.0
      },
      "properties": {
        "src": "assets/e368f6b8d9fa.png",
        "alt": null,
        "objectFit": "contain",
        "filters": {},
        "border": {},
        "shadow": {},
        "animations": [
          {
            "delay": "0.2s",
            "duration": "0.4s",
            "fillMode": "forwards",
            "iterationCount": "1",
            "name": "gwd-gen-tepwgwdanimation_gwd-keyframes_start",
            "timingFunction": "linear"
          }
        ]
      }
    },
    {
      "id": "layer-5",
      "type": "image",
      "name": "content-image",
      "visible": true,
      "locked": false,
      "zIndex": 0,
      "syncStatus": "synced",
      "isTemporary": false,
      "transform": {
        "x": 93.0,
        "y": 101.0,
        "width": 107.0,
        "height": 99.0,
        "rotation": 0.0,
        "scaleX": 1.0,
        "scaleY": 1.0,
        "opacity": 1.0
      },
      "properties": {
        "src": "assets/e368f6b8d9fa.png",
        "alt": null,
        "objectFit": "contain",
        "filters": {},
        "border": {},
        "shadow": {},
        "animations": []
      }
    },
    {
      "id": "Footer",
      "type": "image",
      "name": "content-image",
      "visible": true,
      "locked": false,
      "zIndex": 0,
      "syncStatus": "synced",
      "isTemporary": false,
      "transform": {
        "x": 93.0,
        "y": 101.0,
        "width": 107.0,
        "height": 99.0,
        "rotation": 0.0,
        "scaleX": 1.0,
        "scaleY": 1.0,
        "opacity": 1.0
      },
      "properties": {
        "src": "assets/845fd0e5b9ca.png",
        "alt": null,
        "objectFit": "contain",
        "filters": {},
        "border": {},
        "shadow": {},
        "animations": [
          {
            "delay": "0.2s",
            "duration": "0.4s",
            "fillMode": "forwards",
            "iterationCount": "1",
            "name": "gwd-gen-14a9gwdanimation_gwd-keyframes_start",
            "timingFunction": "linear"
          }
        ]
      }
    },
    {
      "id": "layer-7",
      "type": "image",
      "name": "content-image",
      "visible": true,
      "locked": false,
      "zIndex": 0,
      "syncStatus": "synced",
      "isTemporary": false,
      "transform": {
        "x": 93.0,
        "y": 101.0,
        "width": 107.0,
        "height": 99.0,
        "rotation": 0.0,
        "scaleX": 1.0,
        "scaleY": 1.0,
        "opacity": 1.0
      },
      "properties": {
        "src": "assets/845fd0e5b9ca.png",
        "alt": null,
        "objectFit": "contain",
        "filters": {},
        "border": {},
        "shadow": {},
        "animations": []
      }
    },
    {
      "id": "layer-15",
      "type": "text",
      "name": "body-text",
      "visible": true,
      "locked": false,
      "zIndex": 0,
      "syncStatus": "synced",
      "isTemporary": false,
      "transform": {
        "x": 132.0,
        "y": 140.0,
        "width": 64.0,
        "height": 24.0,
        "rotation": 0.0,
        "scaleX": 1.0,
        "scaleY": 1.0,
        "opacity": 1.0
      },
      "properties": {
        "text": "ENROLL\n         NOW",
        "fontFamily": "Roboto",
        "fontSize": 13.0,
        "fontWeight": "500",
        "fontStyle": "normal",
        "color": "rgb(36, 36, 36)",
        "textAlign": "center",
        "textDecoration": "none",
        "lineHeight": 1.2,
        "letterSpacing": 0,
        "background": {},
        "border": {},
        "shadow": {},
        "animations": []
      }
    },
    {
      "id": "Heading1",
      "type": "heading",
      "name": "heading",
      "visible": true,
      "locked": false,
      "zIndex": 0,
      "syncStatus": "synced",
      "isTemporary": false,
      "transform": {
        "x": 10.0,
        "y": 81.0,
        "width": 110.0,
        "height": 24.0,
        "rotation": 0.0,
        "scaleX": 1.0,
        "scaleY": 1.0,
        "opacity": 1.0
      },
      "properties": {
        "animations": [
          {
            "delay": "0.9s",
            "duration": "0.5s",
            "fillMode": "forwards",
            "iterationCount": "1",
            "name": "gwd-gen-1j11gwdanimation_gwd-keyframes_start",
            "timingFunction": "linear"
          }
        ]
      }
    },
    {
      "id": "Heading2",
      "type": "heading",
      "name": "heading",
      "visible": true,
      "locked": false,
      "zIndex": 0,
      "syncStatus": "synced",
      "isTemporary": false,
      "transform": {
        "x": 10.0,
        "y": 104.0,
        "width": 110.0,
        "height": 24.0,
        "rotation": 0.0,
        "scaleX": 1.0,
        "scaleY": 1.0,
        "opacity": 1.0
      },
      "properties": {
        "animations": [
          {
            "delay": "1.1s",
            "duration": "0.5s",
            "fillMode": "forwards",
            "iterationCount": "1",
            "name": "gwd-gen-r48hgwdanimation_gwd-keyframes_start",
            "timingFunction": "linear"
          }
        ]
      }
    },
    {
      "id": "Tagline",
      "type": "heading",
      "name": "heading",
      "visible": true,
      "locked": false,
      "zIndex": 0,
      "syncStatus": "synced",
      "isTemporary": false,
      "transform": {
        "x": 0.0,
        "y": 130.0,
        "width": 130.0,
        "height": 11.0,
        "rotation": 0.0,
        "scaleX": 1.0,
        "scaleY": 1.0,
        "opacity": 1.0
      },
      "properties": {
        "animations": [
          {
            "delay": "1.5s",
            "duration": "0.5s",
            "fillMode": "forwards",
            "iterationCount": "1",
            "name": "gwd-gen-1tvogwdanimation_gwd-keyframes_start",
            "timingFunction": "linear"
          }
        ]
      }
    },
    {
      "id": "Text",
      "type": "heading",
      "name": "heading",
      "visible": true,
      "locked": false,
      "zIndex": 0,
      "syncStatus": "synced",
      "isTemporary": false,
      "transform": {
        "x": 0.0,
        "y": 150.0,
        "width": 130.0,
        "height": 24.0,
        "rotation": 0.0,
        "scaleX": 1.0,
        "scaleY": 1.0,
        "opacity": 1.0
      },
      "properties": {
        "animations": [
          {
            "delay": "2.2s",
            "duration": "0.5s",
            "fillMode": "forwards",
            "iterationCount": "1",
            "name": "gwd-gen-1kzagwdanimation_gwd-keyframes_start",
            "timingFunction": "linear"
          }
        ]
      }
    },
    {
      "id": "Logo",
      "type": "image",
      "name": "logo",
      "visible": true,
      "locked": false,
      "zIndex": 0,
      "syncStatus": "synced",
      "isTemporary": false,
      "transform": {
        "x": 40.0,
        "y": 42.0,
        "width": 50.0,
        "height": 33.0,
        "rotation": 0.0,
        "scaleX": 1.0,
        "scaleY": 1.0,
        "opacity": 1.0
      },
      "properties": {
        "src": "assets/8a1e00ae0172.png",
        "alt": null,
        "objectFit": "contain",
        "filters": {},
        "border": {},
        "shadow": {},
        "animations": [
          {
            "delay": "1.9s",
            "duration": "0.3s",
            "fillMode": "forwards",
            "iterationCount": "1",
            "name": "gwd-gen-15axgwdanimation_gwd-keyframes_start",
            "timingFunction": "linear"
          }
        ]
      }
    },
    {
      "id": "Call-To-Action",
      "type": "interactive",
      "name": "call-to-action",
      "visible": true,
      "locked": false,
      "zIndex": 0,
      "syncStatus": "synced",
      "isTemporary": false,
      "transform": {
        "x": 130.0,
        "y": 117.0,
        "width": 66.0,
        "height": 67.0,
        "rotation": 0.0,
        "scaleX": 1.0,
        "scaleY": 1.0,
        "opacity": 1.0
      },
      "properties": {
        "animations": [
          {
            "delay": "2.6s",
            "duration": "0.4s",
            "fillMode": "forwards",
            "iterationCount": "1",
            "name": "gwd-gen-6zaogwdanimation_gwd-keyframes_start",
            "timingFunction": "linear"
          }
        ]
      }
    },
    {
      "id": "TapArea",
      "type": "interaction",
      "name": "clickable-area",
      "visible": true,
      "locked": false,
      "zIndex": 0,
      "syncStatus": "synced",
      "isTemporary": false,
      "transform": {
        "x": 0.0,
        "y": 0.0,
        "width": 200.0,
        "height": 200.0,
        "rotation": 0.0,
        "scaleX": 1.0,
        "scaleY": 1.0,
        "opacity": 1.0
      },
      "properties": {
        "animations": []
      }
    }
  ],
  "thumbnail": "assets/screenshot.png"
}